ipools-1.0.1.dist-info/licenses/LICENSE
ippool/__init__.py
ippool/__main__.py
ippool/cli.py
ippool/ippool.py
ippool/iprange.py
ippool/ipv4.py
ippool/ipv6.py
ippool/utils.py
ipools-1.0.1.dist-info/METADATA
ipools-1.0.1.dist-info/WHEEL
ipools-1.0.1.dist-info/entry_points.txt
ipools-1.0.1.dist-info/top_level.txt
ipools-1.0.1.dist-info/RECORD
