Metadata-Version: 2.4
Name: ipools
Version: 1.0.1
Summary: Efficient IP address pool management and operations for IPv4/IPv6 networks.
Author: Theunsafe, tutu
Author-email: jackyspy <jackyspy@hotmail.com>
License-Expression: MIT
Project-URL: Homepage, https://github.com/jackyspy/ippool
Project-URL: Repository, https://github.com/jackyspy/ippool
Project-URL: Documentation, https://github.com/jackyspy/ippool
Project-URL: Bug Tracker, https://github.com/jackyspy/ippool/issues
Keywords: ip,network,range,pool,cidr,ipv4,ipv6
Classifier: Development Status :: 5 - Production/Stable
Classifier: Intended Audience :: Developers
Classifier: Operating System :: OS Independent
Classifier: Programming Language :: Python :: 3
Classifier: Programming Language :: Python :: 3.7
Classifier: Programming Language :: Python :: 3.8
Classifier: Programming Language :: Python :: 3.9
Classifier: Programming Language :: Python :: 3.10
Classifier: Programming Language :: Python :: 3.11
Classifier: Programming Language :: Python :: 3.12
Classifier: Topic :: Software Development :: Libraries :: Python Modules
Classifier: Topic :: System :: Networking
Requires-Python: >=3.7
License-File: LICENSE
Provides-Extra: dev
Requires-Dist: pytest>=6.0; extra == "dev"
Requires-Dist: pytest-benchmark>=4.0; extra == "dev"
Requires-Dist: pytest-cov>=3.0; extra == "dev"
Requires-Dist: black>=22.0; extra == "dev"
Requires-Dist: flake8>=4.0; extra == "dev"
Requires-Dist: mypy>=0.950; extra == "dev"
Provides-Extra: test
Requires-Dist: pytest>=6.0; extra == "test"
Requires-Dist: pytest-benchmark>=4.0; extra == "test"
Requires-Dist: pytest-cov>=3.0; extra == "test"
Dynamic: license-file
